observability_utils/__init__.py
observability_utils/__main__.py
observability_utils/_version.py
observability_utils/tracing/__init__.py
observability_utils/tracing/asserting_exporter.py
observability_utils/tracing/decorators.py
observability_utils/tracing/helpers.py
observability_utils-0.1.5.dist-info/licenses/LICENSE
observability_utils-0.1.5.dist-info/METADATA
observability_utils-0.1.5.dist-info/WHEEL
observability_utils-0.1.5.dist-info/entry_points.txt
observability_utils-0.1.5.dist-info/top_level.txt
observability_utils-0.1.5.dist-info/RECORD
