Metadata-Version: 2.4
Name: observability-utils
Version: 0.1.5
Summary: A set of functions to reduce the boilerplate required to add observability to your service of module
Author-email: Keith Ralphs <keith.ralphs@diamond.ac.uk>
License:                                  Apache License
Project-URL: GitHub, https://github.com/DiamondLightSource/observability-utils
Classifier: Development Status :: 3 - Alpha
Classifier: License :: OSI Approved :: Apache Software License
Classifier: Programming Language :: Python :: 3.10
Classifier: Programming Language :: Python :: 3.11
Requires-Python: >=3.10
License-File: LICENSE
Requires-Dist: fastapi[all]
Requires-Dist: opentelemetry-distro
Requires-Dist: opentelemetry-instrumentation-fastapi
Requires-Dist: opentelemetry-exporter-otlp
Requires-Dist: stomp.py
Provides-Extra: dev
Requires-Dist: copier; extra == "dev"
Requires-Dist: pipdeptree; extra == "dev"
Requires-Dist: pre-commit; extra == "dev"
Requires-Dist: pyright; extra == "dev"
Requires-Dist: pytest; extra == "dev"
Requires-Dist: pytest-cov; extra == "dev"
Requires-Dist: ruff; extra == "dev"
Requires-Dist: tox-direct; extra == "dev"
Requires-Dist: types-mock; extra == "dev"
Dynamic: license-file
